waterpointsmap/__init__.py
waterpointsmap/waterpointsmap.py
waterpointsmap-0.0.2.dist-info/LICENSE
waterpointsmap-0.0.2.dist-info/METADATA
waterpointsmap-0.0.2.dist-info/WHEEL
waterpointsmap-0.0.2.dist-info/top_level.txt
waterpointsmap-0.0.2.dist-info/RECORD
