Metadata-Version: 2.1
Name: waterpointsmap
Version: 0.0.2
Summary: map of location of poor people and nearest water points
Home-page: https://github.com/andrewtolutaiwo/waterpointsmap
Author: Tolu Taiwo
Author-email: tolutaiwo75@gmail.com
License: MIT license
Keywords: waterpointsmap
Classifier: Development Status :: 2 - Pre-Alpha
Classifier: Intended Audience :: Developers
Classifier: License :: OSI Approved :: MIT License
Classifier: Natural Language :: English
Classifier: Programming Language :: Python :: 3
Classifier: Programming Language :: Python :: 3.7
Classifier: Programming Language :: Python :: 3.8
Classifier: Programming Language :: Python :: 3.9
Classifier: Programming Language :: Python :: 3.10
Requires-Python: >=3.7
License-File: LICENSE
